{
	"backtraceGraph" : 
	{
		"commands" : 
		[
			"INSTALL",
			"install",
			"sfml_export_targets"
		],
		"files" : 
		[
			"framework/external/sfml/CMakeLists.txt",
			"framework/external/sfml/cmake/Macros.cmake"
		],
		"nodes" : 
		[
			{
				"file" : 0
			},
			{
				"command" : 0,
				"file" : 0,
				"line" : 311,
				"parent" : 0
			},
			{
				"command" : 0,
				"file" : 0,
				"line" : 311,
				"parent" : 0
			},
			{
				"command" : 0,
				"file" : 0,
				"line" : 311,
				"parent" : 0
			},
			{
				"command" : 0,
				"file" : 0,
				"line" : 311,
				"parent" : 0
			},
			{
				"command" : 0,
				"file" : 0,
				"line" : 311,
				"parent" : 0
			},
			{
				"command" : 0,
				"file" : 0,
				"line" : 311,
				"parent" : 0
			},
			{
				"command" : 1,
				"file" : 0,
				"line" : 318,
				"parent" : 0
			},
			{
				"command" : 1,
				"file" : 0,
				"line" : 418,
				"parent" : 0
			},
			{
				"command" : 1,
				"file" : 0,
				"line" : 419,
				"parent" : 0
			},
			{
				"command" : 2,
				"file" : 0,
				"line" : 529,
				"parent" : 0
			},
			{
				"command" : 1,
				"file" : 1,
				"line" : 445,
				"parent" : 10
			},
			{
				"command" : 1,
				"file" : 1,
				"line" : 449,
				"parent" : 10
			}
		]
	},
	"installers" : 
	[
		{
			"backtrace" : 1,
			"component" : "Unspecified",
			"destination" : "/usr/local/pkgconfig",
			"paths" : 
			[
				"build/framework/external/sfml/tools/pkg-config/sfml-all.pc"
			],
			"type" : "file"
		},
		{
			"backtrace" : 2,
			"component" : "Unspecified",
			"destination" : "/usr/local/pkgconfig",
			"paths" : 
			[
				"build/framework/external/sfml/tools/pkg-config/sfml-system.pc"
			],
			"type" : "file"
		},
		{
			"backtrace" : 3,
			"component" : "Unspecified",
			"destination" : "/usr/local/pkgconfig",
			"paths" : 
			[
				"build/framework/external/sfml/tools/pkg-config/sfml-window.pc"
			],
			"type" : "file"
		},
		{
			"backtrace" : 4,
			"component" : "Unspecified",
			"destination" : "/usr/local/pkgconfig",
			"paths" : 
			[
				"build/framework/external/sfml/tools/pkg-config/sfml-graphics.pc"
			],
			"type" : "file"
		},
		{
			"backtrace" : 5,
			"component" : "Unspecified",
			"destination" : "/usr/local/pkgconfig",
			"paths" : 
			[
				"build/framework/external/sfml/tools/pkg-config/sfml-audio.pc"
			],
			"type" : "file"
		},
		{
			"backtrace" : 6,
			"component" : "Unspecified",
			"destination" : "/usr/local/pkgconfig",
			"paths" : 
			[
				"build/framework/external/sfml/tools/pkg-config/sfml-network.pc"
			],
			"type" : "file"
		},
		{
			"backtrace" : 7,
			"component" : "devel",
			"destination" : ".",
			"paths" : 
			[
				"framework/external/sfml/include"
			],
			"type" : "directory"
		},
		{
			"backtrace" : 8,
			"component" : "Unspecified",
			"destination" : "share/doc/SFML",
			"paths" : 
			[
				"framework/external/sfml/license.md"
			],
			"type" : "file"
		},
		{
			"backtrace" : 9,
			"component" : "Unspecified",
			"destination" : "share/doc/SFML",
			"paths" : 
			[
				"framework/external/sfml/readme.md"
			],
			"type" : "file"
		},
		{
			"backtrace" : 11,
			"component" : "Unspecified",
			"destination" : "lib/cmake/SFML",
			"exportName" : "SFMLConfigExport",
			"exportTargets" : 
			[
				{
					"id" : "sfml-system::@61e52fe2b376ab479238",
					"index" : 4
				},
				{
					"id" : "sfml-network::@c0343bec1d0155e2b7e1",
					"index" : 3
				}
			],
			"paths" : 
			[
				"framework/external/sfml/CMakeFiles/Export/3937c6824958577f216dad0a66bc6149/SFMLStaticTargets.cmake"
			],
			"type" : "export"
		},
		{
			"backtrace" : 12,
			"component" : "devel",
			"destination" : "lib/cmake/SFML",
			"paths" : 
			[
				"build/framework/external/sfml/SFMLConfig.cmake",
				"build/framework/external/sfml/SFMLConfigDependencies.cmake",
				"build/framework/external/sfml/SFMLConfigVersion.cmake"
			],
			"type" : "file"
		}
	],
	"paths" : 
	{
		"build" : "framework/external/sfml",
		"source" : "framework/external/sfml"
	}
}
